.hgignore
.hgtags
LICENSE
MANIFEST.in
Makefile
README.rst
RELEASE.rst
setup.py
sahriswiki/__init__.py
sahriswiki/argparse.py
sahriswiki/auth.py
sahriswiki/config.py
sahriswiki/dbm.py
sahriswiki/env.py
sahriswiki/errors.py
sahriswiki/feedformatter.py
sahriswiki/highlight.py
sahriswiki/i18n.py
sahriswiki/main.py
sahriswiki/pagetypes.py
sahriswiki/reprconf.py
sahriswiki/root.py
sahriswiki/schema.py
sahriswiki/search.py
sahriswiki/storage.py
sahriswiki/tools.py
sahriswiki/unrepr.py
sahriswiki/utils.py
sahriswiki.egg-info/PKG-INFO
sahriswiki.egg-info/SOURCES.txt
sahriswiki.egg-info/dependency_links.txt
sahriswiki.egg-info/entry_points.txt
sahriswiki.egg-info/requires.txt
sahriswiki.egg-info/top_level.txt
sahriswiki/creoleparser/__init__.py
sahriswiki/creoleparser/core.py
sahriswiki/creoleparser/dialects.py
sahriswiki/creoleparser/elements.py
sahriswiki/htdocs/favicon.ico
sahriswiki/htdocs/css/about.css
sahriswiki/htdocs/css/code.css
sahriswiki/htdocs/css/pygments.css
sahriswiki/htdocs/css/screen.css
sahriswiki/htdocs/css/wiki.css
sahriswiki/htdocs/img/python.png
sahriswiki/htdocs/img/valid-css.png
sahriswiki/htdocs/img/valid-xhtml10.png
sahriswiki/htdocs/img/icons/COPYING
sahriswiki/htdocs/img/icons/COPYRIGHTS
sahriswiki/htdocs/img/icons/PythonPowered.png
sahriswiki/htdocs/img/icons/alert.png
sahriswiki/htdocs/img/icons/angry.png
sahriswiki/htdocs/img/icons/attention.png
sahriswiki/htdocs/img/icons/biggrin.png
sahriswiki/htdocs/img/icons/checkmark.png
sahriswiki/htdocs/img/icons/devil.png
sahriswiki/htdocs/img/icons/draft.png
sahriswiki/htdocs/img/icons/edit-conflict.png
sahriswiki/htdocs/img/icons/frown.png
sahriswiki/htdocs/img/icons/icon-error.png
sahriswiki/htdocs/img/icons/icon-info.png
sahriswiki/htdocs/img/icons/idea.png
sahriswiki/htdocs/img/icons/moin-addquicklink-big.png
sahriswiki/htdocs/img/icons/moin-addquicklink.png
sahriswiki/htdocs/img/icons/moin-attach.png
sahriswiki/htdocs/img/icons/moin-badinter.png
sahriswiki/htdocs/img/icons/moin-bottom.png
sahriswiki/htdocs/img/icons/moin-deleted.png
sahriswiki/htdocs/img/icons/moin-delquicklink-big.png
sahriswiki/htdocs/img/icons/moin-delquicklink.png
sahriswiki/htdocs/img/icons/moin-diff-big.png
