Metadata-Version: 1.0
Name: sahriswiki
Version: 0.8.1
Summary: A Lightweight Wiki / CMS / Blogging Engine using circuits.web
Home-page: http://bitbucket.org/prologic/sahriswiki/
Author: James Mills
Author-email: James Mills, prologic at shortcircuit dot net dot au
License: MIT
Download-URL: http://bitbucket.org/prologic/sahriswiki/downloads/
Keywords: wiki cms blog engine circuits
Platform: POSIX
Classifier: Development Status :: 4 - Beta
Classifier: Environment :: Plugins
Classifier: Environment :: Web Environment
Classifier: Intended Audience :: Developers
Classifier: Intended Audience :: Information Technology
Classifier: License :: OSI Approved :: MIT License
Classifier: Natural Language :: English
Classifier: Operating System :: POSIX :: Linux
Classifier: Programming Language :: Python :: 2.6
Classifier: Topic :: Internet :: WWW/HTTP :: WSGI :: Application
